gather/__init__.py
gather/__main__.py
gather/gather.py
powerBI_EIO_NPP-0.2.6.1.dist-info/METADATA
powerBI_EIO_NPP-0.2.6.1.dist-info/WHEEL
powerBI_EIO_NPP-0.2.6.1.dist-info/entry_points.txt
powerBI_EIO_NPP-0.2.6.1.dist-info/top_level.txt
powerBI_EIO_NPP-0.2.6.1.dist-info/RECORD
