Metadata-Version: 2.1
Name: powerBI-EIO-NPP
Version: 0.2.6.1
Summary: Script for gathering data from other apiclients and refreshing Power BI workbooks
Home-page: https://github.com/NilPujolPorta/powerBI-EIO-NPP
Author: Nil Pujol Porta
Author-email: nilpujolporta@gmail.com
License: GNU
Platform: UNKNOWN
Requires-Dist: keyboard
Requires-Dist: argparse
Requires-Dist: setuptools (>=42)
Requires-Dist: wheel
Requires-Dist: CatbackupAPI-NPP (>=1.5.7)
Requires-Dist: HyperbackupAPI2-NPP (>=0.1.4)
Requires-Dist: PandoraFMS-API (>=1.3.5)
Requires-Dist: SynologyAPI-NPP (>=1.7.5)
Requires-Dist: PowerBI-refresher-NPP (>=1.1.9)
Requires-Dist: wget
